terraform_model/__init__.py
terraform_model/model/CfnModel.py
terraform_model/model/Data.py
terraform_model/model/EC2Instance.py
terraform_model/model/EC2NetworkInterface.py
terraform_model/model/EC2SecurityGroup.py
terraform_model/model/EC2SecurityGroupEgress.py
terraform_model/model/EC2SecurityGroupIngress.py
terraform_model/model/ElasticLoadBalancingLoadBalancer.py
terraform_model/model/ElasticLoadBalancingV2LoadBalancer.py
terraform_model/model/IAMGroup.py
terraform_model/model/IAMManagedPolicy.py
terraform_model/model/IAMPolicy.py
terraform_model/model/IAMRole.py
terraform_model/model/IAMUser.py
terraform_model/model/LambdaPrincipal.py
terraform_model/model/Locals.py
terraform_model/model/ModelElement.py
terraform_model/model/Output.py
terraform_model/model/Parameter.py
terraform_model/model/Policy.py
terraform_model/model/PolicyDocument.py
terraform_model/model/Principal.py
terraform_model/model/Provider.py
terraform_model/model/References.py
terraform_model/model/S3BucketPolicy.py
terraform_model/model/SNSTopicPolicy.py
terraform_model/model/SQSQueuePolicy.py
terraform_model/model/Statement.py
terraform_model/model/__init__.py
terraform_model/parser/CfnParser.py
terraform_model/parser/Ec2InstanceParser.py
terraform_model/parser/Ec2NetworkInterfaceParser.py
terraform_model/parser/Error.py
terraform_model/parser/IamGroupParser.py
terraform_model/parser/IamRoleParser.py
terraform_model/parser/IamUserParser.py
terraform_model/parser/LoadBalancerParser.py
terraform_model/parser/LoadBalancerV2Parser.py
terraform_model/parser/ParserError.py
terraform_model/parser/ParserRegistry.py
terraform_model/parser/PolicyDocumentParser.py
terraform_model/parser/SecurityGroupParser.py
terraform_model/parser/TransformRegistry.py
terraform_model/parser/WithPolicyDocumentParser.py
terraform_model/parser/__init__.py
terraform_model/schema/AWS_CloudFront_Distribution.yml
terraform_model/schema/AWS_EC2_Instance.yml
terraform_model/schema/AWS_EC2_NetworkInterface.yml
terraform_validator-0.6.42.dist-info/LICENSE
terraform_validator-0.6.42.dist-info/METADATA
terraform_validator-0.6.42.dist-info/WHEEL
terraform_validator-0.6.42.dist-info/entry_points.txt
terraform_validator-0.6.42.dist-info/top_level.txt
terraform_validator-0.6.42.dist-info/RECORD
